djiutil/__init__.py
djiutil/__main__.py
djiutil/convert.py
djiutil/files.py
djiutil-1.0.3.dist-info/LICENSE
djiutil-1.0.3.dist-info/METADATA
djiutil-1.0.3.dist-info/WHEEL
djiutil-1.0.3.dist-info/entry_points.txt
djiutil-1.0.3.dist-info/RECORD
