Metadata-Version: 2.1
Name: djiutil
Version: 1.0.3
Summary: Manipulate files created by DJI drones
Home-page: https://github.com/will2dye4/djiutil.git
License: MIT
Keywords: dji,dji air,dji drone,dji mavic,mavic,mavic pro
Author: William Dye
Requires-Python: >=3.11,<4.0
Classifier: License :: OSI Approved :: MIT License
Classifier: Programming Language :: Python :: 3
Classifier: Programming Language :: Python :: 3.11
Requires-Dist: srt (>=3.5.3,<4.0.0)
Requires-Dist: tabulate (>=0.9.0,<0.10.0)
Project-URL: Repository, https://github.com/will2dye4/djiutil.git
